txkazoo/__init__.py
txkazoo/_version.py
txkazoo/client.py
txkazoo/log.py
txkazoo/recipe/__init__.py
txkazoo/recipe/partitioner.py
txkazoo/recipe/watchers.py
txkazoo/recipe/test/__init__.py
txkazoo/recipe/test/test_watchers.py
txkazoo/test/__init__.py
txkazoo/test/test_client.py
txkazoo/test/test_log.py
txkazoo/test/test_txkazoo.py
txkazoo/test/test_version.py
txkazoo/test/util.py
txkazoo-0.0.6b2.dist-info/DESCRIPTION.rst
txkazoo-0.0.6b2.dist-info/METADATA
txkazoo-0.0.6b2.dist-info/metadata.json
txkazoo-0.0.6b2.dist-info/RECORD
txkazoo-0.0.6b2.dist-info/top_level.txt
txkazoo-0.0.6b2.dist-info/WHEEL
txkazoo-0.0.6b2.dist-info/zip-safe
